ffdb/__init__.py
ffdb/exceptions.py
ffdb/ffindex.py
ffdb/py.typed
ffdb/seq.py
ffdb/scripts/__init__.py
ffdb/scripts/collect.py
ffdb/scripts/combine.py
ffdb/scripts/fasta.py
ffdb/scripts/join_concat.py
ffdb/scripts/order.py
ffdb/scripts/select.py
ffdb/scripts/split.py
ffindexdb-0.0.1.dist-info/LICENSE
ffindexdb-0.0.1.dist-info/METADATA
ffindexdb-0.0.1.dist-info/WHEEL
ffindexdb-0.0.1.dist-info/entry_points.txt
ffindexdb-0.0.1.dist-info/top_level.txt
ffindexdb-0.0.1.dist-info/RECORD
