Metadata-Version: 2.1
Name: ffindexdb
Version: 0.0.1
Summary: Utility scripts to work with ffindex databases files.
Home-page: https://github.com/darcyabjones/ffdb
Author: Darcy Jones
Author-email: darcy.a.jones@postgrad.curtin.edu.au
License: Apache 2.0
Keywords: bioinformatics
Platform: UNKNOWN
Classifier: Development Status :: 4 - Beta
Classifier: License :: OSI Approved :: Apache Software License
Classifier: Programming Language :: Python :: 3
Classifier: Programming Language :: Python :: 3.6
Classifier: Programming Language :: Python :: 3.7
Classifier: Programming Language :: Python :: 3.8
Provides-Extra: dev
Requires-Dist: check-manifest ; extra == 'dev'
Provides-Extra: test
Requires-Dist: coverage ; extra == 'test'
Requires-Dist: mypy ; extra == 'test'
